kryten_shell/__init__.py
kryten_shell/__main__.py
kryten_shell/app.py
kryten_shell/client.py
kryten_shell/commands/__init__.py
kryten_shell/commands/base.py
kryten_shell/commands/builtins.py
kryten_shell/commands/parser.py
kryten_shell/config.py
kryten_shell/Kryten_Shell_v0_1_0_2025-12-17T01_20_38_826211.svg
kryten_shell/theme.tcss
kryten_shell/views/__init__.py
kryten_shell/views/chat.py
kryten_shell/views/events.py
kryten_shell/views/kv_inspector.py
kryten_shell/views/playlist.py
kryten_shell/views/status.py
kryten_shell/views/users.py
kryten_shell/widgets/__init__.py
kryten_shell/widgets/command_input.py
kryten_shell-0.1.4.dist-info/entry_points.txt
kryten_shell-0.1.4.dist-info/licenses/LICENSE
kryten_shell-0.1.4.dist-info/METADATA
kryten_shell-0.1.4.dist-info/WHEEL
kryten_shell-0.1.4.dist-info/RECORD
