Metadata-Version: 2.4
Name: kryten-shell
Version: 0.1.4
Summary: Interactive TUI shell for inspecting and controlling the Kryten ecosystem
License: MIT
License-File: LICENSE
Keywords: kryten,cytube,tui,shell,textual
Author: grobertson
Requires-Python: >=3.10,<4.0
Classifier: Development Status :: 3 - Alpha
Classifier: Environment :: Console
Classifier: Intended Audience :: Developers
Classifier: License :: OSI Approved :: MIT License
Classifier: Operating System :: OS Independent
Classifier: Programming Language :: Python :: 3
Classifier: Programming Language :: Python :: 3.10
Classifier: Programming Language :: Python :: 3.11
Classifier: Programming Language :: Python :: 3.12
Classifier: Programming Language :: Python :: 3.13
Classifier: Programming Language :: Python :: 3.14
Classifier: Topic :: System :: Monitoring
Classifier: Topic :: Utilities
Requires-Dist: click (>=8.1.0,<9.0.0)
Requires-Dist: kryten-py (>=0.9.12,<0.10.0)
Requires-Dist: orjson (>=3.10.0,<4.0.0)
Requires-Dist: platformdirs (>=4.3.0,<5.0.0)
Requires-Dist: rich (>=13.9.0,<14.0.0)
Requires-Dist: textual (>=3.0.0,<4.0.0)
